{
    "AX": {
        "error": 0.06055744780451652, 
        "fit": "average_SEM", 
        "value": -0.05245050164710847
    }, 
    "CDD": {
        "error": 9.229746618381314e-05, 
        "fit": "average_SEM", 
        "value": 4.201874889531609e-05
    }, 
    "H1": {
        "error": 0.11528608220795883, 
        "fit": "average_SEM", 
        "value": -0.05726425038921661
    }, 
    "H2": {
        "error": 0.1155906975278079, 
        "fit": "average_SEM", 
        "value": -0.08264703788765473
    }, 
    "L1": {
        "error": 0.11688247161747686, 
        "fit": "average_SEM", 
        "value": -0.09247127385315253
    }, 
    "L2": {
        "error": 0.13064202690701152, 
        "fit": "average_SEM", 
        "value": -0.06595659075612276
    }
}