{
    "AX": {
        "error": 0.005284566443023021, 
        "fit": "average", 
        "value": -0.08862997241085395
    }, 
    "CDD": {
        "error": 1.7537577763658515e-05, 
        "fit": "average", 
        "value": 0.00019787011933658505
    }, 
    "H1": {
        "error": 0.011976026445072965, 
        "fit": "average", 
        "value": -0.0010411672328094332
    }, 
    "H2": {
        "error": 0.010023485727727268, 
        "fit": "average", 
        "value": -0.21867507500962044
    }, 
    "L1": {
        "error": 0.009987730969919143, 
        "fit": "average", 
        "value": -0.05732788556779269
    }, 
    "L2": {
        "error": 0.02106230830849082, 
        "fit": "average", 
        "value": -0.10682949945718671
    }
}