{
    "AX": {
        "error": 0.005430549283145256, 
        "fit": "average", 
        "value": -0.07459026678358592
    }, 
    "CDD": {
        "error": 2.937985421016345e-05, 
        "fit": "average", 
        "value": 0.0005964116328565675
    }, 
    "H1": {
        "error": 0.01070798806899008, 
        "fit": "average", 
        "value": 0.019837725943458888
    }, 
    "H2": {
        "error": 0.010274528738625444, 
        "fit": "average", 
        "value": -0.2113368825909371
    }, 
    "L1": {
        "error": 0.011216250725221852, 
        "fit": "average", 
        "value": -0.04832592458405997
    }, 
    "L2": {
        "error": 0.02305835187577257, 
        "fit": "average", 
        "value": -0.0977486343481966
    }
}