{
    "AX": {
        "error": 0.004350873799187378, 
        "fit": "average", 
        "value": -0.09651743743351189
    }, 
    "CDD": {
        "error": 8.70381599864533e-06, 
        "fit": "average", 
        "value": 8.200022759612896e-05
    }, 
    "H1": {
        "error": 0.009687904353585294, 
        "fit": "average", 
        "value": -0.08306491772398455
    }, 
    "H2": {
        "error": 0.007690093691221443, 
        "fit": "average", 
        "value": -0.26712583965725367
    }, 
    "L1": {
        "error": 0.009018250383169958, 
        "fit": "average", 
        "value": -0.05334456409877425
    }, 
    "L2": {
        "error": 0.017894260562084967, 
        "fit": "average", 
        "value": -0.12044177372331938
    }
}