{
    "AX": {
        "error": 0.005490446873660147, 
        "fit": "average", 
        "value": -0.07694992734856593
    }, 
    "CDD": {
        "error": 1.7546897841623627e-05, 
        "fit": "average", 
        "value": 0.0002819076243364786
    }, 
    "H1": {
        "error": 0.01137110441740026, 
        "fit": "average", 
        "value": -0.006037115579238162
    }, 
    "H2": {
        "error": 0.010011428419549755, 
        "fit": "average", 
        "value": -0.24989799393030504
    }, 
    "L1": {
        "error": 0.011241211938000093, 
        "fit": "average", 
        "value": -0.06698636381217209
    }, 
    "L2": {
        "error": 0.022332101068577213, 
        "fit": "average", 
        "value": -0.11082860412037311
    }
}