{
    "AX": {
        "error": 0.005763106713347415, 
        "fit": "average", 
        "value": -0.09201006773510016
    }, 
    "CDD": {
        "error": 2.1868011041305076e-06, 
        "fit": "average", 
        "value": -8.403753190577845e-06
    }, 
    "H1": {
        "error": 0.009714979168241801, 
        "fit": "average", 
        "value": -0.05679063711140771
    }, 
    "H2": {
        "error": 0.010802463598611372, 
        "fit": "average", 
        "value": -0.23055480862773645
    }, 
    "L1": {
        "error": 0.011331191813659108, 
        "fit": "average", 
        "value": -0.055169384912005626
    }, 
    "L2": {
        "error": 0.019134532864238496, 
        "fit": "average", 
        "value": -0.10175264227824907
    }
}