{
    "Ar36": {
        "error": 0.0072190071118553613, 
        "fit": "parabolic", 
        "value": 0.35303645500427683
    }, 
    "Ar37": {
        "error": 0.22058307769019678, 
        "fit": "linear", 
        "value": 1.263017846589928
    }, 
    "Ar38": {
        "error": 0.1151892807293371, 
        "fit": "linear", 
        "value": 0.27234424612102703
    }, 
    "Ar39": {
        "error": 0.061593751129019887, 
        "fit": "parabolic", 
        "value": 4.7917790419568691
    }, 
    "Ar40": {
        "error": 0.16432358995265989, 
        "fit": "parabolic", 
        "value": 111.51978642488791
    }, 
    "Ar41": {
        "error": 0.11531425282083718, 
        "fit": "average_SEM", 
        "value": 0.023890607119392372
    }
}