{
    "AX": {
        "error": 0.005440340961388961, 
        "fit": "average", 
        "value": -0.08923936175221267
    }, 
    "CDD": {
        "error": 1.8298324870592162e-05, 
        "fit": "average", 
        "value": 0.00023224909922040145
    }, 
    "H1": {
        "error": 0.010677724197165114, 
        "fit": "average", 
        "value": -0.015020236050865303
    }, 
    "H2": {
        "error": 0.009846001533605136, 
        "fit": "average", 
        "value": -0.23075647657193865
    }, 
    "L1": {
        "error": 0.010210044234568607, 
        "fit": "average", 
        "value": -0.0985325445382235
    }, 
    "L2": {
        "error": 0.02330317771442327, 
        "fit": "average", 
        "value": -0.10258353900086756
    }
}