{
    "Ar36": {
        "error": 0.005548207249863062, 
        "fit": "parabolic", 
        "value": 6.0072059909814683
    }, 
    "Ar37": {
        "error": 0.025359175964157606, 
        "fit": "linear", 
        "value": -0.067616849904106463
    }, 
    "Ar38": {
        "error": 0.012133968239711922, 
        "fit": "linear", 
        "value": 1.088416916190899
    }, 
    "Ar39": {
        "error": 0.011014916456995013, 
        "fit": "parabolic", 
        "value": -0.050437523548050978
    }, 
    "Ar40": {
        "error": 0.093591165988752195, 
        "fit": "parabolic", 
        "value": 1814.5176973099228
    }, 
    "Ar41": {
        "error": 0.0053462779235972065, 
        "fit": "average", 
        "value": -0.22390664992621168
    }
}