{
    "Ar36": {
        "error": 0.0013526060706618936, 
        "fit": "parabolic", 
        "value": 0.73244762361493621
    }, 
    "Ar37": {
        "error": 0.014246691182460091, 
        "fit": "linear", 
        "value": 47.939964877880115
    }, 
    "Ar38": {
        "error": 0.010275030886483001, 
        "fit": "linear", 
        "value": 1.2656367850436787
    }, 
    "Ar39": {
        "error": 0.011067198702914506, 
        "fit": "parabolic", 
        "value": 38.642955463508088
    }, 
    "Ar40": {
        "error": 0.027689530075903097, 
        "fit": "parabolic", 
        "value": 219.6400733759601
    }, 
    "Ar41": {
        "error": 0.0046176439359555017, 
        "fit": "average", 
        "value": -0.04586435976564341
    }
}