{
    "Ar36": {
        "error": 0.0013924165671309304, 
        "fit": "parabolic", 
        "value": 0.71806353474705631
    }, 
    "Ar37": {
        "error": 0.027854095913688849, 
        "fit": "linear", 
        "value": 5.0106566310627159
    }, 
    "Ar38": {
        "error": 0.0094500341100667521, 
        "fit": "linear", 
        "value": 0.40417022293031346
    }, 
    "Ar39": {
        "error": 0.0090554873285096336, 
        "fit": "parabolic", 
        "value": 6.7437943779207412
    }, 
    "Ar40": {
        "error": 0.027016196165064812, 
        "fit": "parabolic", 
        "value": 223.88230855451519
    }, 
    "Ar41": {
        "error": 0.0044969257512072211, 
        "fit": "average", 
        "value": -0.25128213782775372
    }
}