{
    "Ar36": {
        "error": 0.0012678972594255416, 
        "fit": "parabolic", 
        "value": 0.57832197819605424
    }, 
    "Ar37": {
        "error": 0.018875247813273953, 
        "fit": "linear", 
        "value": 19.207524362741449
    }, 
    "Ar38": {
        "error": 0.009992765548184894, 
        "fit": "linear", 
        "value": 0.53228234186088552
    }, 
    "Ar39": {
        "error": 0.010496256988080804, 
        "fit": "parabolic", 
        "value": 27.83246086713207
    }, 
    "Ar40": {
        "error": 0.025579226840509978, 
        "fit": "parabolic", 
        "value": 174.49373930436178
    }, 
    "Ar41": {
        "error": 0.0042762353409410885, 
        "fit": "average", 
        "value": -0.26186695897534568
    }
}