{
    "Ar36": {
        "error": 0.025483657097625758, 
        "fit": "parabolic", 
        "value": 4.7915183318928793
    }, 
    "Ar37": {
        "error": 0.14164459157798381, 
        "fit": "linear", 
        "value": 7.8148922553597924
    }, 
    "Ar38": {
        "error": 0.11650896758226265, 
        "fit": "linear", 
        "value": 3.2597419101637954
    }, 
    "Ar39": {
        "error": 0.12534831382885453, 
        "fit": "parabolic", 
        "value": 149.32311173949745
    }, 
    "Ar40": {
        "error": 0.4463591437557341, 
        "fit": "parabolic", 
        "value": 1488.1139055681538
    }, 
    "Ar41": {
        "error": 0.11490470307343319, 
        "fit": "average_SEM", 
        "value": -0.0069664925050165038
    }
}